baselayer/__init__.py
baselayer-0.0.0.dist-info/METADATA
baselayer-0.0.0.dist-info/WHEEL
baselayer-0.0.0.dist-info/top_level.txt
baselayer-0.0.0.dist-info/RECORD
