Metadata-Version: 2.4
Name: baselayer
Version: 0.0.0
Summary: PyPi version coming soon; see GH for existing releases
Author-email: Stéfan van der Walt <stefanv@berkeley.edu>
Project-URL: Homepage, https://cesium-ml.org/baselayer/
Project-URL: Documentation, https://cesium-ml.org/baselayer/
Project-URL: Repository, https://github.com/cesium-ml/baselayer
Project-URL: Issues, https://github.com/cesium-ml/baselayer/issues
